MANIFEST.in
README.md
setup.py
pyoprf/__init__.py
pyoprf/multiplexer.py
pyoprf/noisexk.py
pyoprf.egg-info/PKG-INFO
pyoprf.egg-info/SOURCES.txt
pyoprf.egg-info/dependency_links.txt
pyoprf.egg-info/requires.txt
pyoprf.egg-info/top_level.txt
tests/test.py