Metadata-Version: 2.4
Name: pyoprf
Version: 0.9.3
Summary: python bindings for liboprf
Home-page: https://github.com/stef/liboprf/python
Author: Stefan Marsiske
Author-email: toprf@ctrlc.hu
License: LGPLv3
Classifier: Development Status :: 4 - Beta
Classifier: License :: OSI Approved :: GNU Lesser General Public License v3 or later (LGPLv3+)
Classifier: Topic :: Security :: Cryptography
Classifier: Topic :: Security
Requires-Dist: pysodium
Requires-Dist: SecureString
Requires-Dist: pyserial
Requires-Dist: pyudev
Requires-Dist: ble_serial
Requires-Dist: pyserial-asyncio
Dynamic: author
Dynamic: author-email
Dynamic: classifier
Dynamic: description
Dynamic: description-content-type
Dynamic: home-page
Dynamic: license
Dynamic: requires-dist
Dynamic: summary
